<?xml version="1.0" encoding="utf-8"?>
<!DOCTYPE hibernate-mapping PUBLIC "-//Hibernate/Hibernate Mapping DTD 3.0//EN"
                                   "http://hibernate.sourceforge.net/hibernate-mapping-3.0.dtd">
	<!--
		Mapping file autogenerated by MyEclipse Persistence Tools
		identity:由底层数据库生成标识符。identity是由数据库自己生成的，但这个主键必须设置为自增长，前提条件是低层数据库支持自动增长字段类型
		increment:由hibernate管理主键，自动以递增的方式生成标识符，每次增量为1。其在每次插入前取得一个当前最大的id+１作为主键，该主键必须为Integer类型
	-->
<hibernate-mapping>
	<class name="com.lxt2.common.common.model.TlUser" table="TL_USER" dynamic-insert="true" dynamic-update="true">
		<id name="numuserid" type="java.lang.Integer">
			<column name="NUMUSERID" precision="20" scale="0" />
			<generator class="sequence">
				<param name="sequence">TLSEQ_USER</param>
			</generator>
		</id>
		<property name="vc2usercode" type="java.lang.String" >
			<column name="VC2USERCODE" length="50" />
		</property>
		<property name="vc2username" type="java.lang.String" >
			<column name="VC2USERNAME" length="50" />
		</property>
		<property name="vc2uaccount" type="java.lang.String">
			<column name="VC2UACCOUNT" length="50" />
		</property>
		<property name="vc2upassword" type="java.lang.String">
			<column name="VC2UPASSWORD" length="50" />
		</property>
		<property name="vc2mobile" type="java.lang.String">
			<column name="VC2MOBILE" length="50" />
		</property>
		<property name="vc2email" type="java.lang.String">
			<column name="VC2EMAIL" length="100" />
		</property>
		<property name="vc2extendcode" type="java.lang.String">
			<column name="VC2EXTENDCODE" length="100" />
		</property>
		<property name="numusrc" type="java.lang.Integer">
			<column name="NUMUSRC" length="2" />
		</property>
		<property name="numtotallimit" type="java.lang.Integer">
			<column name="NUMTOTALLIMIT" length="20" />
		</property>
		<property name="nummonthlimit" type="java.lang.Integer">
			<column name="NUMMONTHLIMIT" length="20" />
		</property>
		<property name="numweeklimit" type="java.lang.Integer">
			<column name="NUMWEEKLIMIT" length="20" />
		</property>
		<property name="numdaylimit" type="java.lang.Integer">
			<column name="NUMDAYLIMIT" length="20" />
		</property>
		<property name="numstate" type="java.lang.Integer">
			<column name="NUMSTATE" length="2" />
		</property>
		<property name="numbusinessid" type="java.lang.Integer">
			<column name="NUMBUSINESSID" length="20" />
		</property>
		<property name="numcreator" type="java.lang.Integer">
			<column name="NUMCREATOR" length="20" />
		</property>
		<property name="datcreatetime" type="java.util.Date">
			<column name="DATCREATETIME" />
		</property>
		<property name="numlastmodifyuser" type="java.lang.Integer">
			<column name="NUMLASTMODIFYUSER" length="20" />
		</property>
		<property name="datlastmodifytime" type="java.util.Date">
			<column name="DATLASTMODIFYTIME" />
		</property>
		<property name="vc2isfirstlogin" type="java.lang.String">
			<column name="VC2ISFIRSTLOGIN" length="1" />
		</property>
		<property name="numpositionid" type="java.lang.Integer">
			<column name="NUMPOSITIONID" length="20" />
		</property>
		<property name="numemployeeid" type="java.lang.Integer">
			<column name="NUMEMPLOYEEID" length="20" />
		</property>
		<property name="numdepartid" type="java.lang.Integer">
			<column name="NUMDEPARTID" length="20" />
		</property>
		<property name="vc2phone" type="java.lang.String">
			<column name="VC2PHONE" length="50" />
		</property>
		<property name="vc2ordercode" type="java.lang.String">
			<column name="VC2ORDERCODE" length="20" />
		</property>
		<property name="numtype" type="java.lang.Integer">
			<column name="NUMTYPE" length="2" />
		</property>
		<property name="vc2signature" type="java.lang.String">
			<column name="VC2SIGNATURE" length="50" />
		</property>
		<property name="vc2mobilelist" type="java.lang.String">
			<column name="VC2MOBILELIST" length="200" />
		</property>
		<property name="numcheckstate" type="java.lang.Integer">
			<column name="NUMCHECKSTATE" length="1" />
		</property>
		<property name="numchecklevle" type="java.lang.Integer">
			<column name="NUMCHECKLEVLE" length="1" />
		</property>
		<property name="numnodeid" type="java.lang.Integer">
			<column name="NUMNODEID" length="20" />
		</property>
		
	</class>
</hibernate-mapping>
