<?xml version="1.0" encoding="utf-8"?>
<!DOCTYPE hibernate-mapping PUBLIC "-//Hibernate/Hibernate Mapping DTD 3.0//EN"
"http://hibernate.sourceforge.net/hibernate-mapping-3.0.dtd">
<hibernate-mapping>
<!--Mapping file autogenerated by TOSO2.0;-->
<class name="com.yxt.business.model.mms.TlMmsSendgroup" table="TL_MMS_SENDGROUP">

    <!--彩信发送批次，取自序列TLSEQ_MMS_SENDGROUP(NUMBER:22)-->
    
      <id name="numsendgroupid" type="java.lang.Integer">
      <column name="NUMSENDGROUPID" precision="22" scale="0" />
      <generator class="sequence">
      <param name="sequence">TLSEQ_MMS_SENDGROUP</param>
      </generator>
      </id>
    
    <!--彩信内容编号(NUMBER:22)-->
    
      <property name="numcontentid" type="java.lang.Integer">
      <column name="NUMCONTENTID" length="22"/>
      </property>
    
    <!--客户组ID，如果是非用户组发送则空(NUMBER:22)-->
    
      <property name="numusergroupid" type="java.lang.Integer">
      <column name="NUMUSERGROUPID" length="22"/>
      </property>
    
</class>
</hibernate-mapping>
  